{
  "slug": "pulling-your-website-up-by-your-twitter-bootstraps",
  "title": "Pulling Your Website Up By Your Twitter Bootstraps",
  "_links": {
    "self": { "href": "/2014/sessions/pulling-your-website-up-by-your-twitter-bootstraps" },
    "event": { "href": "/2014/" },
    "track": { "href": "/2014/tracks/web" },
    "space": { "href": "/2014/spaces/room-4" },
    "timePeriod": { "href": "/2014/time-periods/1545" },
    "level": { "href": "/2014/levels/100" },
    "speaker": [
      { "href": "/2014/speakers/kyle-mitofsky" }
    ]
  }
}
